db_artifact/__init__.py
db_artifact/artifact_converger.py
db_artifact/converge_artifact.py
db_artifact/docker_converge_entrypoint.py
db_artifact/sceptre/__init__.py
db_artifact/sceptre/config/__init__.py
db_artifact/sceptre/config/config.yaml
db_artifact/sceptre/config/prod/__init__.py
db_artifact/sceptre/templates/__init__.py
db_artifact/sceptre/templates/clone.yaml
db_artifact_builder/Dockerfile
db_artifact_builder/__init__.py
db_artifact_builder/build_artifact.py
db_artifact_builder/config_exception.py
db_artifact_builder/db_artifact_builder_config.py
db_artifact_builder/image_builder.py
db_artifact_builder/network_discovery.py
db_artifact_builder/sceptre_parameter_generator.py
database_artifact_factory-0.1.0.dist-info/METADATA
database_artifact_factory-0.1.0.dist-info/WHEEL
database_artifact_factory-0.1.0.dist-info/entry_points.txt
database_artifact_factory-0.1.0.dist-info/top_level.txt
database_artifact_factory-0.1.0.dist-info/RECORD
