Metadata-Version: 2.1
Name: database-artifact-factory
Version: 0.1.0
Summary: An RDS database factory for rapidly creating database copies
Home-page: https://github.com/stelligent/database-artifact-factory
Author: Eric Kascic
Author-email: eric.kascic@stelligent.com
License: MIT
Platform: UNKNOWN
Requires-Python: >=3.6
Requires-Dist: boto3 (==1.12.26)
Requires-Dist: docker
